llama_index/llms/bedrock_converse/__init__.py
llama_index/llms/bedrock_converse/base.py
llama_index/llms/bedrock_converse/utils.py
llama_index_llms_bedrock_converse-0.12.4.dist-info/METADATA
llama_index_llms_bedrock_converse-0.12.4.dist-info/WHEEL
llama_index_llms_bedrock_converse-0.12.4.dist-info/licenses/LICENSE
llama_index_llms_bedrock_converse-0.12.4.dist-info/RECORD
